{
  "data": {
    "total": 704,
    "pagenum": "1",
    "goods": [
      {
        "goods_id": 1589,
        "cat_id": null,
        "goods_name": "达瓦达瓦",
        "goods_price": 11,
        "goods_number": 1,
        "goods_weight": 1,
        "goods_state": null,
        "add_time": 1670987684,
        "upd_time": 1670987684,
        "hot_mumber": 0,
        "is_promote": false,
        "cat_one_id": null,
        "cat_two_id": null,
        "cat_three_id": null
      },
      {
        "goods_id": 1588,
        "cat_id": null,
        "goods_name": "asc",
        "goods_price": 123,
        "goods_number": 0,
        "goods_weight": 11,
        "goods_state": null,
        "add_time": 1670987519,
        "upd_time": 1670987519,
        "hot_mumber": 0,
        "is_promote": false,
        "cat_one_id": null,
        "cat_two_id": null,
        "cat_three_id": null
      },
      {
        "goods_id": 1582,
        "cat_id": null,
        "goods_name": "azxa",
        "goods_price": 121,
        "goods_number": 12,
        "goods_weight": 12,
        "goods_state": null,
        "add_time": 1670987330,
        "upd_time": 1670987330,
        "hot_mumber": 0,
        "is_promote": false,
        "cat_one_id": null,
        "cat_two_id": null,
        "cat_three_id": null
      },
      {
        "goods_id": 1577,
        "cat_id": null,
        "goods_name": "DFG R",
        "goods_price": 455,
        "goods_number": 66,
        "goods_weight": 56,
        "goods_state": null,
        "add_time": 1670986840,
        "upd_time": 1670986840,
        "hot_mumber": 0,
        "is_promote": false,
        "cat_one_id": null,
        "cat_two_id": null,
        "cat_three_id": null
      },
      {
        "goods_id": 1556,
        "cat_id": null,
        "goods_name": "苦涩咖啡22333",
        "goods_price": 133,
        "goods_number": 133,
        "goods_weight": 133,
        "goods_state": null,
        "add_time": 1670986770,
        "upd_time": 1670986770,
        "hot_mumber": 0,
        "is_promote": false,
        "cat_one_id": null,
        "cat_two_id": null,
        "cat_three_id": null
      },
      {
        "goods_id": 1568,
        "cat_id": null,
        "goods_name": "23234234",
        "goods_price": 1234,
        "goods_number": 123,
        "goods_weight": 123,
        "goods_state": null,
        "add_time": 1670985999,
        "upd_time": 1670985999,
        "hot_mumber": 0,
        "is_promote": false,
        "cat_one_id": null,
        "cat_two_id": null,
        "cat_three_id": null
      },
      {
        "goods_id": 1560,
        "cat_id": null,
        "goods_name": "大冰箱老大了",
        "goods_price": 1000111,
        "goods_number": 100011,
        "goods_weight": 65535,
        "goods_state": null,
        "add_time": 1670984874,
        "upd_time": 1670984874,
        "hot_mumber": 0,
        "is_promote": false,
        "cat_one_id": null,
        "cat_two_id": null,
        "cat_three_id": null
      },
      {
        "goods_id": 1557,
        "cat_id": null,
        "goods_name": "芜湖的起飞123",
        "goods_price": 11,
        "goods_number": 1,
        "goods_weight": 11,
        "goods_state": null,
        "add_time": 1670984234,
        "upd_time": 1670984234,
        "hot_mumber": 0,
        "is_promote": false,
        "cat_one_id": null,
        "cat_two_id": null,
        "cat_three_id": null
      },
      {
        "goods_id": 1554,
        "cat_id": null,
        "goods_name": "我是广少",
        "goods_price": 114514,
        "goods_number": 114514,
        "goods_weight": 65535,
        "goods_state": null,
        "add_time": 1670983736,
        "upd_time": 1670983736,
        "hot_mumber": 0,
        "is_promote": false,
        "cat_one_id": null,
        "cat_two_id": null,
        "cat_three_id": null
      },
      {
        "goods_id": 1550,
        "cat_id": null,
        "goods_name": "哥哥123",
        "goods_price": 300,
        "goods_number": 250,
        "goods_weight": 250,
        "goods_state": null,
        "add_time": 1670982777,
        "upd_time": 1670982777,
        "hot_mumber": 0,
        "is_promote": false,
        "cat_one_id": null,
        "cat_two_id": null,
        "cat_three_id": null
      }
    ]
  },
  "meta": { "msg": "获取成功", "status": 200 }
}
